allauth_ens/__init__.py
allauth_ens/adapter.py
allauth_ens/apps.py
allauth_ens/tests.py
allauth_ens/urls.py
allauth_ens/utils.py
allauth_ens/views.py
allauth_ens/management/__init__.py
allauth_ens/management/commands/__init__.py
allauth_ens/management/commands/deprecate_clippers.py
allauth_ens/management/commands/install_longterm.py
allauth_ens/providers/__init__.py
allauth_ens/providers/clipper/__init__.py
allauth_ens/providers/clipper/models.py
allauth_ens/providers/clipper/provider.py
allauth_ens/providers/clipper/tests.py
allauth_ens/providers/clipper/urls.py
allauth_ens/providers/clipper/views.py
allauth_ens/static/allauth_ens/authens.js
allauth_ens/static/allauth_ens/ie.css
allauth_ens/static/allauth_ens/print.css
allauth_ens/static/allauth_ens/screen.css
allauth_ens/static/allauth_ens/fonts/index.css
allauth_ens/static/allauth_ens/fonts/roboto-bold.ttf
allauth_ens/static/allauth_ens/fonts/roboto-regular.ttf
allauth_ens/static/allauth_ens/fonts/roboto-slab-regular.ttf
allauth_ens/static/allauth_ens/images/64px-Chevron_left_font_awesome.svg.png
allauth_ens/static/allauth_ens/images/Chevron_left_font_awesome.svg
allauth_ens/static/allauth_ens/images/clipper.jpeg
allauth_ens/static/vendor/font-awesome/4.7.0/css/font-awesome.css
allauth_ens/static/vendor/font-awesome/4.7.0/css/font-awesome.min.css
allauth_ens/static/vendor/font-awesome/4.7.0/fonts/fontawesome-webfont.eot
allauth_ens/static/vendor/font-awesome/4.7.0/fonts/fontawesome-webfont.svg
allauth_ens/static/vendor/font-awesome/4.7.0/fonts/fontawesome-webfont.ttf
allauth_ens/static/vendor/font-awesome/4.7.0/fonts/fontawesome-webfont.woff
allauth_ens/static/vendor/font-awesome/4.7.0/fonts/fontawesome-webfont.woff2
allauth_ens/static/vendor/jquery/3.2.1/jquery-3.2.1.slim.min.js
allauth_ens/templates/account/account_inactive.html
allauth_ens/templates/account/email.html
allauth_ens/templates/account/email_confirm.html
allauth_ens/templates/account/login.html
allauth_ens/templates/account/logout.html
django_allauth_ens-1.1.2.dist-info/LICENSE
django_allauth_ens-1.1.2.dist-info/METADATA
django_allauth_ens-1.1.2.dist-info/WHEEL
django_allauth_ens-1.1.2.dist-info/top_level.txt
django_allauth_ens-1.1.2.dist-info/RECORD
